z3c.insist-1.5.7-py3.10-nspkg.pth
z3c/insist/__init__.py
z3c/insist/configure.zcml
z3c/insist/enforce.py
z3c/insist/enftest.py
z3c/insist/insist.py
z3c/insist/insist.txt
z3c/insist/interfaces.py
z3c/insist/perftest.py
z3c/insist/testing.py
z3c/insist/tests/__init__.py
z3c/insist/tests/test_enforce.py
z3c/insist/tests/test_insist.py
z3c.insist-1.5.7.dist-info/LICENSE
z3c.insist-1.5.7.dist-info/METADATA
z3c.insist-1.5.7.dist-info/WHEEL
z3c.insist-1.5.7.dist-info/entry_points.txt
z3c.insist-1.5.7.dist-info/namespace_packages.txt
z3c.insist-1.5.7.dist-info/top_level.txt
z3c.insist-1.5.7.dist-info/RECORD
