Metadata-Version: 2.1
Name: z3c.insist
Version: 1.5.7
Summary: Persistence to ini Files
Home-page: http://pypi.python.org/pypi/z3c.insist
Author: Shoobx, Inc.
Author-email: dev@shoobx.com
License: ZPL 2.1
Keywords: configuration dump serialization
Classifier: License :: OSI Approved :: Zope Public License
Classifier: Development Status :: 2 - Pre-Alpha
Classifier: Intended Audience :: Developers
Classifier: Programming Language :: Python
Classifier: Programming Language :: Python :: 3
Classifier: Programming Language :: Python :: 3.7
Classifier: Programming Language :: Python :: 3.8
Classifier: Programming Language :: Python :: 3.9
Classifier: Programming Language :: Python :: 3.10
Classifier: Programming Language :: Python :: 3.11
Classifier: Natural Language :: English
Classifier: Operating System :: OS Independent
License-File: LICENSE
Requires-Dist: setuptools
Requires-Dist: zope.schema
Requires-Dist: zope.component
Requires-Dist: zope.lifecycleevent
Requires-Dist: iso8601
Provides-Extra: enforce
Requires-Dist: watchdog (<4.0.0,>=3.0.0) ; extra == 'enforce'
Provides-Extra: test
Requires-Dist: zope.testing ; extra == 'test'
Requires-Dist: coverage ; extra == 'test'
Requires-Dist: python-subunit ; extra == 'test'
Requires-Dist: junitxml ; extra == 'test'
Requires-Dist: mock ; extra == 'test'
Requires-Dist: pytz ; extra == 'test'
